[{"joinToken": "canada_5", "players": ["merlin", "percival", "LSA", "minion of mordred/oberon", "morgana"], "tokens": ["15", "42", "44", "35", "72", "1", "4", "81", "83", "11", "93", "92", "99", "21", "69", "68", "9", "48", "75", "18", "37", "76", "5", "27", "66", "12", "28", "40", "55", "91", "24", "60", "59", "87", "2", "29", "51", "3", "73", "14", "38", "97", "17", "49", "56", "89", "58", "0", "77", "47", "53", "22", "30", "96", "84", "54", "95", "20", "43", "67", "33", "90", "13", "52", "80", "25", "86", "74", "65", "79", "34", "70", "63", "26", "36", "31", "41", "98", "94", "45", "50", "10", "85", "82", "64", "78", "46", "62", "39", "7", "16", "8", "71", "57", "6", "88", "32", "61", "23", "19"], "numPlayers": 5}, {"joinToken": "canada_6", "players": ["morgana", "merlin", "minion of mordred/oberon", "percival", "LSA", "LSA"], "tokens": ["9", "61", "93", "72", "42", "51", "41", "92", "84", "3", "90", "33", "49", "62", "30", "96", "31", "69", "19", "74", "89", "15", "12", "76", "4", "28", "38", "13", "67", "35", "86", "99", "68", "36", "21", "24", "11", "78", "5", "81", "0", "55", "60", "65", "70", "39", "18", "32", "27", "63", "14", "37", "91", "87", "34", "66", "59", "1", "47", "23", "44", "53", "54", "80", "82", "25", "10", "26", "20", "83", "95", "46", "77", "75", "50", "58", "94", "56", "48", "22", "71", "29", "88", "40", "79", "97", "16", "6", "8", "98", "43", "7", "45", "73", "2", "64", "52", "17", "85", "57"], "numPlayers": 6}, {"joinToken": "canada_7", "players": ["minion of mordred/oberon", "percival", "minion of mordred/mordred", "merlin", "LSA", "morgana", "LSA"], "tokens": ["39", "85", "46", "69", "14", "99", "43", "53", "73", "96", "91", "33", "59", "19", "47", "38", "56", "49", "64", "4", "72", "21", "42", "11", "25", "40", "67", "82", "76", "86", "37", "13", "10", "44", "80", "79", "81", "61", "2", "5", "65", "97", "32", "71", "88", "1", "74", "41", "7", "98", "58", "3", "8", "26", "23", "27", "89", "68", "6", "84", "35", "51", "57", "54", "45", "70", "16", "78", "36", "52", "12", "90", "62", "60", "17", "63", "75", "92", "9", "83", "0", "30", "34", "24", "94", "48", "87", "28", "18", "93", "22", "20", "29", "31", "95", "15", "66", "55", "77", "50"], "numPlayers": 7}, {"joinToken": "canada_8", "players": ["LSA", "LSA", "merlin", "minion of mordred/mordred", "morgana", "LSA", "percival", "minion of mordred/oberon"], "tokens": ["58", "37", "38", "41", "35", "96", "84", "32", "85", "49", "44", "93", "3", "86", "40", "45", "1", "77", "30", "36", "66", "82", "59", "18", "97", "5", "74", "95", "26", "39", "46", "34", "48", "71", "64", "11", "24", "73", "76", "90", "15", "2", "22", "43", "61", "55", "87", "54", "25", "4", "72", "20", "6", "63", "62", "16", "79", "8", "29", "7", "83", "10", "67", "68", "9", "33", "92", "56", "69", "21", "89", "17", "91", "75", "80", "52", "19", "14", "65", "60", "27", "70", "23", "28", "81", "53", "31", "12", "94", "0", "47", "50", "88", "98", "51", "78", "99", "42", "57", "13"], "numPlayers": 8}, {"joinToken": "canada_9", "players": ["LSA", "LSA", "LSA", "percival", "minion of mordred/mordred", "minion of mordred/oberon", "LSA", "merlin", "morgana"], "tokens": ["39", "50", "4", "73", "41", "55", "56", "3", "13", "6", "77", "96", "44", "74", "61", "19", "76", "15", "14", "10", "2", "16", "80", "46", "72", "97", "58", "8", "51", "11", "48", "65", "43", "42", "98", "40", "7", "17", "52", "79", "87", "84", "34", "27", "30", "57", "69", "68", "59", "1", "32", "82", "21", "86", "71", "26", "33", "91", "20", "47", "60", "37", "0", "54", "24", "49", "29", "90", "92", "83", "66", "9", "18", "88", "70", "81", "38", "35", "53", "23", "99", "64", "67", "95", "93", "45", "62", "94", "36", "89", "63", "31", "5", "85", "25", "12", "22", "75", "28", "78"], "numPlayers": 9}, {"joinToken": "canada_10", "players": ["morgana", "minion of mordred/oberon", "minion of mordred/mordred", "LSA", "LSA", "minion of mordred", "merlin", "LSA", "percival", "LSA"], "tokens": ["42", "31", "5", "91", "2", "26", "47", "24", "56", "46", "65", "70", "87", "75", "8", "76", "43", "11", "92", "41", "37", "72", "38", "53", "16", "49", "57", "93", "19", "52", "45", "59", "55", "15", "79", "60", "17", "89", "0", "99", "36", "96", "73", "35", "30", "34", "58", "82", "48", "81", "13", "67", "32", "9", "83", "29", "6", "27", "7", "54", "33", "78", "23", "51", "4", "28", "69", "84", "12", "10", "3", "22", "62", "20", "39", "21", "61", "90", "50", "77", "66", "74", "40", "97", "68", "94", "18", "71", "80", "88", "44", "85", "63", "86", "25", "95", "98", "64", "1", "14"], "numPlayers": 10}, {"joinToken": "delta_5", "players": ["LSA", "merlin", "morgana", "percival", "minion of mordred/oberon"], "tokens": ["58", "99", "73", "65", "1", "82", "97", "49", "34", "21", "13", "76", "53", "89", "45", "86", "5", "14", "67", "29", "50", "40", "12", "54", "87", "85", "19", "24", "98", "95", "20", "18", "15", "94", "80", "60", "83", "25", "22", "68", "64", "0", "71", "31", "84", "32", "51", "72", "37", "61", "39", "47", "78", "91", "43", "66", "23", "8", "10", "46", "30", "74", "48", "4", "62", "16", "41", "11", "63", "81", "90", "75", "96", "9", "33", "36", "92", "7", "26", "55", "44", "59", "17", "6", "69", "88", "35", "93", "52", "56", "79", "28", "42", "38", "77", "27", "70", "3", "57", "2"], "numPlayers": 5}, {"joinToken": "delta_6", "players": ["merlin", "minion of mordred/oberon", "morgana", "percival", "LSA", "LSA"], "tokens": ["61", "41", "46", "96", "18", "25", "39", "8", "91", "54", "9", "12", "6", "38", "2", "30", "74", "33", "77", "16", "92", "37", "26", "43", "7", "84", "60", "58", "10", "23", "34", "35", "97", "48", "85", "31", "1", "19", "36", "24", "44", "64", "66", "17", "68", "80", "22", "51", "89", "29", "49", "88", "83", "95", "59", "53", "99", "76", "11", "87", "71", "63", "14", "79", "72", "75", "13", "45", "78", "62", "65", "67", "70", "69", "27", "73", "15", "32", "40", "56", "20", "86", "21", "52", "93", "94", "98", "5", "4", "50", "28", "47", "82", "81", "42", "0", "90", "57", "55", "3"], "numPlayers": 6}, {"joinToken": "delta_7", "players": ["morgana", "LSA", "merlin", "minion of mordred/mordred", "minion of mordred/oberon", "LSA", "percival"], "tokens": ["61", "67", "85", "45", "62", "41", "40", "53", "10", "8", "17", "26", "4", "63", "95", "99", "51", "13", "1", "69", "0", "20", "22", "42", "18", "92", "90", "78", "9", "37", "16", "38", "39", "14", "65", "89", "54", "29", "59", "21", "81", "97", "91", "79", "43", "15", "82", "50", "44", "49", "72", "34", "33", "98", "70", "60", "23", "55", "96", "66", "47", "86", "30", "3", "24", "27", "12", "93", "84", "87", "11", "28", "58", "56", "64", "35", "48", "36", "2", "74", "94", "6", "31", "75", "52", "19", "57", "77", "5", "68", "88", "73", "80", "32", "83", "46", "7", "76", "71", "25"], "numPlayers": 7}, {"joinToken": "delta_8", "players": ["LSA", "minion of mordred/mordred", "minion of mordred/oberon", "merlin", "LSA", "morgana", "LSA", "percival"], "tokens": ["75", "41", "87", "15", "68", "47", "19", "18", "22", "77", "21", "34", "24", "80", "25", "10", "54", "29", "6", "67", "65", "17", "98", "56", "95", "2", "60", "12", "28", "14", "82", "4", "20", "64", "32", "92", "40", "26", "97", "36", "63", "69", "46", "16", "66", "90", "99", "94", "93", "86", "91", "62", "45", "8", "76", "85", "89", "52", "11", "23", "74", "44", "61", "3", "35", "27", "7", "70", "84", "31", "13", "1", "51", "9", "57", "55", "38", "53", "5", "50", "58", "71", "81", "96", "88", "48", "72", "37", "39", "49", "83", "59", "0", "78", "79", "42", "73", "30", "43", "33"], "numPlayers": 8}, {"joinToken": "delta_9", "players": ["morgana", "LSA", "LSA", "merlin", "minion of mordred/mordred", "LSA", "LSA", "percival", "minion of mordred/oberon"], "tokens": ["80", "7", "26", "83", "89", "62", "34", "24", "58", "87", "29", "55", "73", "71", "52", "8", "90", "4", "97", "16", "27", "66", "99", "12", "28", "33", "13", "50", "42", "92", "76", "46", "39", "19", "60", "14", "82", "30", "44", "85", "56", "9", "2", "63", "5", "70", "81", "47", "61", "35", "21", "15", "3", "10", "49", "6", "20", "23", "86", "31", "51", "17", "72", "77", "59", "48", "75", "54", "36", "41", "84", "98", "57", "32", "1", "93", "18", "67", "69", "53", "74", "0", "78", "43", "40", "38", "79", "91", "45", "25", "95", "22", "65", "94", "96", "11", "68", "37", "88", "64"], "numPlayers": 9}, {"joinToken": "delta_10", "players": ["minion of mordred/oberon", "LSA", "minion of mordred", "LSA", "morgana", "LSA", "LSA", "merlin", "percival", "minion of mordred/mordred"], "tokens": ["15", "98", "99", "58", "17", "96", "82", "36", "41", "13", "97", "73", "80", "69", "50", "38", "49", "37", "92", "1", "3", "66", "60", "95", "39", "77", "90", "26", "67", "24", "7", "72", "2", "28", "79", "62", "88", "30", "47", "33", "48", "5", "44", "12", "6", "57", "0", "52", "20", "53", "11", "40", "76", "29", "64", "46", "31", "91", "68", "27", "65", "23", "85", "25", "14", "94", "78", "59", "71", "87", "9", "86", "61", "89", "35", "93", "32", "18", "42", "63", "75", "45", "22", "84", "21", "43", "54", "19", "70", "56", "4", "10", "34", "74", "83", "8", "81", "16", "55", "51"], "numPlayers": 10}, {"joinToken": "united_5", "players": ["minion of mordred/oberon", "percival", "morgana", "LSA", "merlin"], "tokens": ["19", "85", "39", "58", "15", "61", "76", "20", "75", "48", "42", "59", "27", "1", "82", "88", "89", "26", "86", "32", "3", "70", "36", "0", "78", "93", "12", "91", "33", "49", "74", "28", "6", "84", "21", "95", "68", "24", "65", "40", "81", "18", "16", "41", "17", "38", "50", "53", "80", "55", "31", "67", "79", "99", "4", "52", "37", "94", "46", "22", "13", "5", "8", "63", "35", "96", "29", "10", "72", "92", "25", "77", "66", "11", "54", "90", "51", "7", "47", "62", "98", "69", "45", "56", "71", "43", "64", "30", "14", "23", "34", "87", "97", "57", "2", "44", "9", "60", "83", "73"], "numPlayers": 5}, {"joinToken": "united_6", "players": ["LSA", "LSA", "minion of mordred/oberon", "percival", "merlin", "morgana"], "tokens": ["21", "43", "14", "19", "0", "55", "20", "65", "97", "88", "35", "66", "48", "9", "27", "61", "25", "67", "1", "13", "37", "79", "15", "87", "58", "72", "12", "2", "62", "26", "29", "34", "23", "69", "68", "83", "7", "40", "85", "80", "64", "46", "93", "73", "90", "44", "4", "8", "22", "57", "10", "81", "99", "5", "11", "38", "94", "84", "18", "78", "39", "30", "31", "95", "96", "60", "77", "63", "41", "36", "50", "33", "91", "42", "59", "56", "17", "89", "47", "6", "82", "92", "32", "51", "70", "3", "49", "45", "98", "52", "54", "28", "16", "71", "53", "76", "74", "86", "75", "24"], "numPlayers": 6}, {"joinToken": "united_7", "players": ["LSA", "percival", "merlin", "minion of mordred/mordred", "morgana", "minion of mordred/oberon", "LSA"], "tokens": ["89", "32", "77", "78", "10", "1", "70", "21", "20", "82", "91", "3", "86", "92", "96", "62", "93", "68", "83", "26", "15", "4", "35", "23", "48", "73", "52", "49", "66", "53", "65", "24", "19", "85", "28", "33", "84", "39", "22", "34", "79", "12", "18", "6", "88", "9", "98", "59", "43", "11", "45", "37", "94", "80", "51", "71", "29", "44", "17", "75", "36", "16", "46", "57", "58", "38", "31", "50", "63", "95", "61", "8", "14", "27", "56", "41", "13", "60", "64", "42", "87", "90", "40", "67", "81", "30", "76", "0", "54", "74", "99", "55", "47", "72", "25", "7", "97", "2", "5", "69"], "numPlayers": 7}, {"joinToken": "united_8", "players": ["LSA", "percival", "minion of mordred/mordred", "morgana", "minion of mordred/oberon", "LSA", "LSA", "merlin"], "tokens": ["61", "48", "74", "65", "53", "71", "56", "4", "76", "86", "75", "72", "87", "19", "17", "83", "55", "14", "39", "50", "47", "97", "6", "68", "58", "96", "37", "70", "16", "38", "54", "12", "67", "62", "35", "59", "18", "34", "88", "22", "85", "5", "95", "30", "3", "44", "29", "60", "99", "73", "1", "91", "41", "89", "11", "32", "26", "40", "9", "77", "0", "43", "49", "8", "98", "51", "27", "10", "90", "82", "66", "93", "25", "7", "92", "79", "69", "94", "78", "33", "24", "63", "21", "42", "64", "80", "45", "81", "36", "57", "52", "13", "31", "28", "23", "84", "46", "15", "2", "20"], "numPlayers": 8}, {"joinToken": "united_9", "players": ["minion of mordred/oberon", "morgana", "LSA", "merlin", "LSA", "LSA", "LSA", "minion of mordred/mordred", "percival"], "tokens": ["44", "26", "67", "30", "16", "54", "1", "57", "56", "35", "88", "38", "99", "86", "58", "82", "62", "20", "61", "18", "42", "66", "60", "75", "21", "15", "89", "90", "72", "85", "34", "94", "83", "93", "23", "69", "28", "3", "51", "10", "81", "9", "95", "97", "12", "76", "13", "11", "33", "59", "17", "19", "74", "29", "78", "45", "6", "96", "4", "27", "37", "55", "36", "79", "49", "0", "22", "91", "39", "71", "24", "5", "84", "46", "7", "48", "73", "80", "31", "47", "43", "41", "8", "50", "63", "52", "2", "68", "25", "65", "14", "77", "92", "53", "64", "98", "87", "32", "70", "40"], "numPlayers": 9}, {"joinToken": "united_10", "players": ["minion of mordred/oberon", "morgana", "LSA", "LSA", "minion of mordred/mordred", "minion of mordred", "LSA", "merlin", "LSA", "percival"], "tokens": ["12", "89", "40", "98", "78", "99", "8", "19", "22", "74", "34", "93", "39", "54", "32", "46", "81", "66", "92", "55", "36", "53", "37", "6", "15", "27", "80", "18", "9", "17", "42", "95", "48", "50", "56", "21", "4", "82", "5", "88", "90", "58", "29", "11", "41", "45", "84", "91", "75", "26", "64", "16", "69", "25", "60", "62", "1", "85", "33", "47", "44", "30", "76", "65", "77", "86", "28", "68", "73", "59", "14", "3", "87", "23", "72", "71", "0", "67", "97", "20", "31", "83", "51", "49", "13", "79", "43", "24", "10", "7", "57", "52", "38", "35", "2", "96", "94", "70", "61", "63"], "numPlayers": 10}, {"joinToken": "frontier_5", "players": ["percival", "merlin", "minion of mordred/oberon", "LSA", "morgana"], "tokens": ["26", "39", "72", "55", "58", "19", "53", "8", "16", "12", "85", "90", "44", "80", "95", "54", "7", "40", "59", "77", "3", "74", "50", "47", "6", "38", "63", "78", "83", "91", "21", "93", "66", "14", "30", "68", "43", "1", "92", "17", "65", "81", "97", "61", "18", "76", "4", "84", "42", "15", "2", "28", "56", "71", "20", "32", "49", "29", "41", "57", "13", "75", "9", "27", "98", "48", "36", "89", "64", "45", "34", "99", "96", "37", "69", "11", "35", "87", "62", "46", "94", "70", "31", "51", "23", "0", "88", "60", "25", "86", "10", "73", "22", "52", "67", "82", "5", "33", "24", "79"], "numPlayers": 5}, {"joinToken": "frontier_6", "players": ["merlin", "LSA", "minion of mordred/oberon", "percival", "morgana", "LSA"], "tokens": ["3", "79", "28", "11", "89", "23", "56", "4", "7", "72", "83", "16", "99", "61", "69", "64", "48", "9", "49", "74", "87", "38", "45", "25", "52", "58", "71", "93", "86", "46", "36", "91", "75", "78", "20", "90", "39", "63", "94", "15", "54", "53", "19", "80", "35", "22", "41", "14", "24", "96", "60", "29", "27", "85", "92", "62", "0", "50", "33", "1", "34", "18", "82", "8", "51", "37", "31", "88", "95", "21", "13", "44", "2", "97", "26", "42", "66", "43", "10", "47", "17", "77", "76", "30", "68", "65", "81", "67", "40", "84", "98", "55", "12", "5", "6", "32", "73", "57", "70", "59"], "numPlayers": 6}, {"joinToken": "frontier_7", "players": ["minion of mordred/oberon", "percival", "LSA", "merlin", "minion of mordred/mordred", "morgana", "LSA"], "tokens": ["55", "7", "1", "47", "90", "57", "92", "64", "76", "91", "22", "87", "51", "17", "96", "72", "29", "79", "16", "98", "26", "24", "44", "95", "93", "46", "36", "35", "59", "77", "69", "61", "89", "53", "52", "32", "49", "34", "33", "86", "38", "99", "10", "20", "39", "2", "75", "41", "8", "9", "13", "42", "68", "85", "94", "19", "88", "21", "31", "78", "40", "0", "67", "83", "56", "5", "43", "30", "81", "97", "58", "23", "45", "84", "18", "65", "71", "66", "50", "73", "25", "14", "80", "37", "27", "12", "60", "11", "48", "4", "3", "70", "54", "28", "74", "82", "62", "6", "63", "15"], "numPlayers": 7}, {"joinToken": "frontier_8", "players": ["LSA", "LSA", "merlin", "minion of mordred/oberon", "percival", "morgana", "LSA", "minion of mordred/mordred"], "tokens": ["6", "68", "2", "28", "56", "73", "32", "35", "92", "42", "41", "62", "8", "20", "77", "49", "71", "85", "27", "59", "82", "10", "94", "5", "80", "40", "91", "14", "55", "48", "7", "76", "65", "30", "3", "93", "21", "64", "75", "18", "50", "86", "66", "31", "43", "78", "79", "96", "34", "52", "44", "0", "98", "36", "12", "45", "1", "89", "87", "70", "51", "16", "4", "58", "99", "22", "25", "46", "95", "29", "23", "60", "88", "67", "53", "24", "33", "61", "54", "11", "90", "63", "97", "74", "17", "37", "57", "81", "47", "26", "38", "15", "69", "83", "9", "39", "72", "84", "13", "19"], "numPlayers": 8}, {"joinToken": "frontier_9", "players": ["LSA", "merlin", "LSA", "morgana", "minion of mordred/mordred", "minion of mordred/oberon", "LSA", "percival", "LSA"], "tokens": ["81", "30", "78", "32", "3", "65", "95", "86", "34", "92", "4", "11", "23", "75", "79", "61", "82", "19", "1", "85", "91", "46", "16", "55", "47", "96", "66", "45", "51", "71", "39", "97", "14", "35", "89", "22", "72", "74", "83", "12", "99", "68", "67", "25", "0", "44", "84", "15", "73", "69", "50", "88", "63", "70", "76", "56", "8", "37", "6", "58", "62", "59", "36", "29", "26", "28", "52", "13", "21", "42", "9", "94", "98", "64", "2", "60", "49", "57", "38", "93", "33", "17", "20", "7", "10", "41", "80", "43", "90", "48", "18", "54", "87", "5", "53", "27", "24", "40", "77", "31"], "numPlayers": 9}, {"joinToken": "frontier_10", "players": ["LSA", "minion of mordred/mordred", "merlin", "minion of mordred/oberon", "LSA", "percival", "minion of mordred", "LSA", "morgana", "LSA"], "tokens": ["35", "51", "4", "84", "53", "47", "58", "77", "17", "49", "76", "46", "72", "18", "67", "99", "7", "1", "34", "92", "64", "89", "33", "83", "45", "8", "79", "12", "32", "5", "28", "78", "98", "94", "66", "97", "68", "65", "27", "11", "60", "15", "55", "80", "86", "75", "73", "88", "90", "2", "14", "21", "22", "70", "31", "85", "41", "13", "91", "52", "71", "3", "23", "95", "69", "87", "40", "42", "63", "36", "81", "43", "9", "82", "44", "30", "96", "56", "29", "19", "37", "50", "6", "0", "61", "57", "48", "39", "25", "93", "24", "10", "59", "16", "26", "38", "20", "54", "62", "74"], "numPlayers": 10}, {"joinToken": "sw_5", "players": ["percival", "LSA", "morgana", "minion of mordred/oberon", "merlin"], "tokens": ["95", "87", "55", "88", "14", "61", "63", "91", "40", "17", "78", "65", "34", "11", "21", "96", "86", "4", "69", "35", "39", "54", "74", "90", "70", "28", "92", "0", "64", "84", "71", "85", "58", "37", "79", "30", "49", "59", "13", "42", "19", "10", "22", "89", "81", "7", "57", "62", "98", "32", "68", "99", "15", "75", "5", "9", "60", "97", "43", "66", "23", "12", "2", "1", "93", "50", "44", "3", "16", "41", "46", "8", "67", "26", "6", "29", "47", "77", "94", "80", "52", "73", "45", "18", "76", "33", "72", "82", "56", "48", "38", "24", "53", "25", "83", "27", "36", "51", "20", "31"], "numPlayers": 5}, {"joinToken": "sw_6", "players": ["morgana", "minion of mordred/oberon", "merlin", "LSA", "percival", "LSA"], "tokens": ["40", "46", "50", "24", "71", "93", "31", "35", "42", "38", "15", "34", "17", "81", "2", "61", "27", "25", "78", "66", "89", "59", "92", "44", "13", "37", "86", "62", "64", "85", "23", "19", "55", "60", "95", "63", "20", "12", "22", "80", "8", "79", "6", "82", "36", "30", "4", "3", "5", "45", "76", "43", "11", "77", "87", "32", "54", "57", "16", "94", "52", "98", "88", "91", "28", "69", "73", "33", "7", "96", "39", "14", "41", "83", "47", "58", "75", "53", "90", "18", "9", "49", "68", "67", "48", "51", "1", "0", "56", "74", "65", "84", "26", "29", "97", "21", "99", "10", "70", "72"], "numPlayers": 6}, {"joinToken": "sw_7", "players": ["percival", "merlin", "LSA", "minion of mordred/mordred", "LSA", "minion of mordred/oberon", "morgana"], "tokens": ["32", "5", "38", "14", "95", "97", "63", "67", "69", "73", "34", "43", "65", "82", "39", "87", "77", "24", "55", "88", "68", "56", "7", "58", "21", "3", "31", "17", "74", "40", "23", "70", "2", "15", "36", "44", "59", "96", "62", "41", "66", "94", "25", "84", "28", "9", "91", "79", "30", "90", "93", "86", "48", "11", "27", "60", "10", "49", "47", "8", "19", "35", "20", "89", "72", "61", "76", "18", "13", "78", "57", "37", "29", "80", "42", "33", "83", "6", "4", "75", "0", "52", "92", "54", "64", "85", "53", "46", "22", "51", "12", "98", "81", "71", "1", "45", "26", "50", "99", "16"], "numPlayers": 7}, {"joinToken": "sw_8", "players": ["morgana", "percival", "LSA", "minion of mordred/mordred", "merlin", "minion of mordred/oberon", "LSA", "LSA"], "tokens": ["4", "7", "98", "78", "93", "83", "2", "30", "1", "26", "90", "70", "15", "49", "24", "46", "40", "8", "20", "62", "21", "80", "44", "77", "97", "95", "99", "75", "63", "58", "25", "6", "55", "42", "82", "54", "92", "13", "51", "86", "29", "11", "32", "52", "57", "43", "48", "96", "45", "37", "66", "64", "41", "87", "65", "10", "84", "27", "74", "91", "5", "88", "12", "19", "94", "60", "3", "38", "33", "39", "79", "18", "67", "22", "47", "61", "14", "28", "34", "59", "9", "31", "50", "81", "72", "35", "73", "0", "23", "85", "76", "69", "71", "68", "53", "56", "36", "89", "16", "17"], "numPlayers": 8}, {"joinToken": "sw_9", "players": ["LSA", "minion of mordred/oberon", "merlin", "percival", "LSA", "morgana", "minion of mordred/mordred", "LSA", "LSA"], "tokens": ["94", "58", "8", "65", "49", "70", "35", "40", "38", "86", "1", "99", "24", "80", "43", "96", "29", "22", "30", "25", "68", "21", "13", "3", "7", "88", "18", "6", "93", "12", "67", "74", "73", "31", "33", "66", "90", "54", "16", "11", "77", "81", "78", "4", "28", "39", "98", "50", "61", "34", "69", "19", "9", "72", "71", "63", "20", "60", "89", "85", "0", "2", "83", "14", "91", "55", "75", "48", "37", "56", "32", "87", "59", "82", "62", "10", "79", "57", "42", "27", "23", "46", "41", "97", "15", "64", "76", "26", "17", "53", "84", "52", "47", "95", "51", "45", "36", "44", "92", "5"], "numPlayers": 9}, {"joinToken": "sw_10", "players": ["minion of mordred", "percival", "LSA", "minion of mordred/mordred", "LSA", "morgana", "merlin", "minion of mordred/oberon", "LSA", "LSA"], "tokens": ["45", "73", "8", "89", "44", "43", "31", "70", "40", "66", "37", "12", "75", "87", "59", "86", "36", "26", "55", "33", "16", "68", "91", "79", "11", "63", "82", "41", "51", "48", "58", "19", "76", "52", "14", "50", "35", "74", "94", "61", "30", "5", "9", "46", "80", "78", "38", "27", "23", "42", "81", "98", "10", "97", "60", "92", "77", "57", "54", "64", "99", "90", "83", "96", "72", "84", "85", "93", "49", "67", "1", "39", "71", "88", "18", "28", "0", "69", "95", "6", "62", "22", "53", "21", "25", "29", "17", "65", "47", "20", "2", "34", "4", "56", "24", "32", "3", "7", "15", "13"], "numPlayers": 10}, {"joinToken": "alaska_5", "players": ["merlin", "percival", "minion of mordred/oberon", "morgana", "LSA"], "tokens": ["65", "22", "90", "15", "40", "28", "6", "16", "23", "82", "27", "50", "74", "38", "91", "44", "88", "58", "98", "55", "48", "12", "37", "57", "3", "51", "25", "99", "1", "72", "79", "81", "56", "26", "42", "9", "41", "66", "43", "34", "5", "54", "13", "80", "21", "63", "33", "95", "71", "8", "11", "35", "73", "61", "70", "52", "10", "59", "86", "0", "4", "20", "89", "60", "31", "67", "85", "97", "53", "7", "19", "17", "14", "2", "18", "76", "49", "39", "96", "77", "47", "75", "68", "94", "62", "64", "30", "84", "24", "29", "36", "46", "92", "83", "93", "45", "87", "32", "69", "78"], "numPlayers": 5}, {"joinToken": "alaska_6", "players": ["LSA", "minion of mordred/oberon", "LSA", "percival", "morgana", "merlin"], "tokens": ["4", "79", "23", "8", "95", "19", "9", "50", "59", "88", "71", "26", "2", "14", "74", "77", "63", "43", "84", "52", "6", "1", "67", "91", "17", "89", "97", "28", "45", "73", "49", "21", "47", "76", "42", "33", "39", "44", "30", "10", "38", "54", "32", "53", "99", "75", "25", "64", "22", "31", "5", "51", "78", "57", "65", "70", "41", "0", "12", "40", "46", "35", "48", "3", "66", "94", "16", "90", "87", "18", "98", "93", "92", "69", "82", "62", "20", "56", "29", "34", "72", "24", "86", "15", "27", "13", "81", "85", "83", "60", "7", "61", "58", "36", "80", "55", "37", "96", "68", "11"], "numPlayers": 6}, {"joinToken": "alaska_7", "players": ["morgana", "merlin", "minion of mordred/mordred", "percival", "minion of mordred/oberon", "LSA", "LSA"], "tokens": ["6", "16", "54", "96", "57", "61", "39", "38", "72", "8", "10", "68", "89", "43", "33", "83", "51", "67", "19", "1", "2", "18", "31", "60", "78", "69", "36", "26", "79", "12", "4", "30", "17", "88", "95", "81", "62", "55", "97", "29", "34", "76", "87", "5", "91", "49", "42", "24", "21", "37", "50", "11", "65", "45", "23", "53", "71", "93", "85", "98", "58", "22", "0", "63", "86", "75", "92", "25", "82", "84", "40", "7", "27", "15", "59", "47", "44", "14", "70", "99", "13", "9", "74", "35", "94", "77", "3", "56", "64", "28", "52", "48", "46", "32", "66", "73", "41", "90", "20", "80"], "numPlayers": 7}, {"joinToken": "alaska_8", "players": ["LSA", "minion of mordred/oberon", "LSA", "percival", "merlin", "minion of mordred/mordred", "LSA", "morgana"], "tokens": ["61", "62", "3", "49", "41", "2", "26", "74", "28", "42", "40", "79", "50", "23", "83", "54", "10", "87", "97", "80", "12", "53", "57", "55", "47", "21", "75", "22", "85", "60", "38", "78", "86", "15", "45", "5", "69", "82", "63", "56", "77", "90", "93", "88", "66", "84", "70", "20", "68", "52", "95", "89", "13", "99", "18", "76", "73", "31", "34", "16", "0", "46", "71", "30", "39", "1", "44", "58", "59", "4", "11", "8", "98", "64", "17", "14", "37", "29", "92", "48", "51", "6", "43", "96", "81", "7", "27", "19", "72", "25", "94", "67", "36", "33", "35", "32", "24", "65", "9", "91"], "numPlayers": 8}, {"joinToken": "alaska_9", "players": ["LSA", "LSA", "minion of mordred/mordred", "minion of mordred/oberon", "LSA", "merlin", "LSA", "morgana", "percival"], "tokens": ["25", "86", "7", "60", "87", "28", "73", "51", "57", "90", "32", "75", "45", "85", "64", "93", "98", "49", "30", "46", "84", "16", "97", "96", "35", "59", "13", "3", "22", "14", "11", "0", "62", "78", "12", "40", "66", "24", "89", "65", "54", "4", "37", "39", "56", "71", "44", "10", "67", "47", "5", "31", "61", "88", "74", "6", "9", "80", "34", "94", "2", "50", "17", "33", "21", "27", "92", "42", "95", "18", "72", "79", "36", "91", "48", "8", "53", "58", "20", "68", "83", "70", "26", "76", "63", "52", "23", "15", "69", "38", "43", "77", "55", "19", "1", "81", "82", "29", "99", "41"], "numPlayers": 9}, {"joinToken": "alaska_10", "players": ["LSA", "minion of mordred", "LSA", "merlin", "LSA", "morgana", "percival", "minion of mordred/mordred", "LSA", "minion of mordred/oberon"], "tokens": ["88", "26", "72", "6", "42", "50", "41", "70", "55", "87", "34", "44", "74", "28", "61", "83", "36", "1", "92", "97", "90", "35", "99", "8", "10", "38", "86", "46", "23", "79", "64", "15", "71", "78", "13", "69", "4", "59", "21", "84", "81", "94", "43", "11", "65", "0", "22", "20", "14", "80", "93", "27", "76", "29", "75", "98", "19", "73", "54", "51", "40", "2", "49", "57", "3", "48", "17", "60", "58", "82", "66", "47", "37", "91", "39", "89", "77", "62", "24", "12", "95", "25", "30", "85", "45", "63", "32", "96", "68", "18", "33", "16", "53", "7", "9", "67", "31", "5", "56", "52"], "numPlayers": 10}, {"joinToken": "american_5", "players": ["merlin", "LSA", "morgana", "percival", "minion of mordred/oberon"], "tokens": ["84", "42", "64", "43", "2", "17", "50", "79", "22", "95", "12", "36", "90", "1", "49", "92", "48", "57", "91", "93", "0", "69", "26", "16", "82", "25", "3", "85", "32", "96", "44", "68", "13", "89", "51", "66", "54", "75", "55", "23", "40", "28", "67", "18", "77", "8", "94", "29", "9", "76", "87", "21", "5", "81", "62", "59", "35", "86", "41", "70", "39", "37", "47", "52", "58", "60", "78", "4", "53", "34", "56", "74", "65", "99", "46", "33", "19", "97", "30", "72", "27", "63", "10", "31", "11", "38", "6", "83", "7", "80", "61", "20", "98", "88", "71", "14", "24", "73", "15", "45"], "numPlayers": 5}, {"joinToken": "american_6", "players": ["minion of mordred/oberon", "LSA", "percival", "morgana", "LSA", "merlin"], "tokens": ["83", "66", "63", "88", "43", "18", "36", "21", "73", "52", "95", "46", "26", "10", "24", "22", "96", "1", "71", "57", "61", "75", "16", "25", "64", "27", "14", "81", "65", "48", "34", "12", "37", "84", "11", "53", "77", "49", "44", "82", "72", "51", "59", "50", "67", "55", "19", "32", "93", "23", "45", "90", "87", "47", "60", "70", "91", "40", "69", "38", "3", "8", "20", "30", "0", "35", "41", "79", "89", "76", "97", "74", "29", "92", "28", "42", "78", "9", "33", "4", "80", "31", "2", "13", "54", "15", "86", "17", "56", "6", "58", "68", "5", "7", "94", "98", "99", "85", "39", "62"], "numPlayers": 6}, {"joinToken": "american_7", "players": ["morgana", "LSA", "minion of mordred/mordred", "minion of mordred/oberon", "LSA", "merlin", "percival"], "tokens": ["68", "96", "18", "63", "41", "51", "93", "9", "43", "55", "58", "91", "34", "64", "80", "23", "45", "39", "66", "53", "24", "57", "69", "16", "73", "67", "19", "50", "33", "26", "30", "86", "42", "61", "70", "21", "99", "90", "88", "77", "82", "3", "71", "46", "38", "49", "89", "36", "31", "92", "32", "48", "83", "29", "6", "8", "97", "40", "85", "74", "7", "4", "20", "84", "44", "60", "15", "28", "0", "25", "13", "52", "47", "62", "95", "72", "17", "56", "59", "78", "37", "54", "79", "75", "14", "22", "65", "87", "98", "94", "10", "81", "1", "12", "76", "27", "5", "35", "2", "11"], "numPlayers": 7}, {"joinToken": "american_8", "players": ["minion of mordred/oberon", "morgana", "merlin", "minion of mordred/mordred", "LSA", "LSA", "LSA", "percival"], "tokens": ["63", "0", "5", "16", "6", "99", "35", "47", "90", "67", "21", "44", "79", "77", "17", "14", "81", "33", "80", "10", "39", "42", "66", "22", "31", "87", "59", "57", "89", "70", "62", "97", "83", "1", "26", "18", "12", "85", "94", "45", "23", "53", "74", "32", "60", "30", "9", "34", "84", "78", "27", "68", "72", "98", "64", "36", "13", "61", "25", "75", "7", "19", "92", "2", "58", "3", "86", "82", "56", "8", "48", "46", "28", "76", "88", "41", "52", "43", "49", "29", "65", "55", "38", "95", "54", "40", "69", "11", "37", "91", "73", "4", "20", "71", "50", "96", "24", "93", "51", "15"], "numPlayers": 8}, {"joinToken": "american_9", "players": ["LSA", "minion of mordred/oberon", "LSA", "merlin", "LSA", "LSA", "morgana", "minion of mordred/mordred", "percival"], "tokens": ["93", "27", "98", "28", "84", "23", "33", "83", "99", "52", "54", "16", "66", "13", "11", "59", "53", "1", "37", "67", "31", "97", "95", "49", "78", "3", "7", "94", "79", "81", "29", "76", "77", "20", "82", "14", "91", "41", "5", "50", "48", "10", "46", "89", "62", "88", "39", "8", "58", "36", "18", "68", "70", "15", "35", "30", "32", "69", "26", "40", "21", "25", "51", "64", "75", "63", "73", "47", "24", "6", "74", "12", "65", "17", "92", "90", "85", "57", "55", "61", "60", "72", "71", "19", "44", "80", "56", "22", "96", "34", "4", "45", "86", "2", "42", "0", "38", "43", "9", "87"], "numPlayers": 9}, {"joinToken": "american_10", "players": ["minion of mordred/mordred", "percival", "morgana", "minion of mordred", "LSA", "LSA", "LSA", "LSA", "minion of mordred/oberon", "merlin"], "tokens": ["24", "85", "49", "55", "44", "59", "95", "51", "2", "31", "81", "52", "8", "63", "92", "70", "3", "77", "47", "9", "30", "88", "25", "29", "28", "75", "21", "84", "11", "0", "18", "12", "97", "90", "69", "79", "68", "58", "36", "82", "64", "57", "80", "34", "67", "96", "60", "27", "54", "93", "15", "10", "39", "16", "74", "76", "5", "17", "1", "91", "62", "48", "6", "45", "61", "33", "38", "46", "43", "98", "32", "22", "37", "26", "35", "78", "56", "86", "66", "99", "94", "4", "14", "23", "41", "13", "89", "19", "7", "71", "72", "65", "53", "87", "40", "42", "50", "73", "20", "83"], "numPlayers": 10}, {"joinToken": "spirit_5", "players": ["LSA", "morgana", "minion of mordred/oberon", "merlin", "percival"], "tokens": ["6", "28", "72", "20", "42", "37", "27", "90", "85", "75", "17", "46", "68", "88", "95", "55", "74", "91", "23", "51", "77", "38", "44", "89", "93", "26", "58", "36", "30", "66", "73", "59", "92", "56", "48", "62", "41", "7", "78", "98", "11", "57", "1", "64", "16", "83", "45", "40", "47", "61", "87", "19", "9", "0", "50", "5", "99", "3", "8", "54", "81", "31", "10", "79", "12", "43", "34", "94", "65", "4", "15", "14", "86", "25", "49", "76", "53", "97", "39", "70", "29", "63", "22", "60", "67", "18", "69", "84", "82", "33", "35", "80", "32", "21", "71", "96", "52", "2", "24", "13"], "numPlayers": 5}, {"joinToken": "spirit_6", "players": ["LSA", "morgana", "merlin", "minion of mordred/oberon", "percival", "LSA"], "tokens": ["97", "86", "92", "22", "11", "55", "47", "54", "76", "39", "65", "96", "1", "94", "17", "69", "35", "34", "72", "82", "31", "83", "23", "81", "29", "24", "48", "16", "51", "57", "21", "30", "73", "20", "56", "36", "50", "60", "32", "89", "88", "91", "87", "90", "71", "98", "58", "3", "40", "66", "2", "95", "44", "42", "0", "18", "10", "74", "68", "7", "14", "85", "37", "27", "99", "79", "41", "49", "67", "25", "26", "46", "19", "9", "77", "13", "33", "52", "45", "12", "75", "6", "63", "84", "28", "4", "93", "62", "61", "8", "53", "78", "80", "15", "59", "64", "43", "70", "5", "38"], "numPlayers": 6}, {"joinToken": "spirit_7", "players": ["percival", "LSA", "minion of mordred/oberon", "LSA", "merlin", "minion of mordred/mordred", "morgana"], "tokens": ["10", "41", "27", "5", "28", "76", "7", "25", "22", "53", "16", "79", "0", "59", "95", "55", "9", "45", "6", "96", "86", "42", "26", "72", "37", "20", "1", "40", "99", "83", "62", "2", "85", "97", "82", "8", "54", "11", "23", "74", "69", "48", "92", "91", "31", "64", "36", "47", "50", "39", "18", "98", "21", "77", "46", "67", "13", "94", "3", "93", "51", "49", "56", "58", "15", "32", "61", "34", "44", "63", "52", "71", "57", "89", "33", "19", "4", "60", "38", "80", "43", "35", "70", "87", "12", "68", "78", "17", "30", "66", "84", "75", "81", "65", "73", "29", "88", "14", "90", "24"], "numPlayers": 7}, {"joinToken": "spirit_8", "players": ["LSA", "LSA", "minion of mordred/mordred", "merlin", "percival", "minion of mordred/oberon", "LSA", "morgana"], "tokens": ["80", "1", "52", "73", "94", "45", "98", "58", "46", "79", "11", "12", "38", "48", "95", "68", "42", "85", "77", "14", "63", "3", "86", "93", "40", "29", "59", "81", "30", "56", "51", "70", "0", "84", "50", "22", "32", "89", "27", "20", "62", "35", "6", "24", "36", "21", "10", "25", "18", "53", "87", "88", "23", "64", "92", "28", "71", "43", "34", "66", "13", "49", "19", "78", "4", "96", "76", "41", "97", "44", "9", "75", "47", "72", "74", "7", "90", "5", "54", "16", "61", "55", "26", "91", "8", "39", "31", "65", "60", "2", "17", "37", "99", "57", "15", "69", "33", "83", "82", "67"], "numPlayers": 8}, {"joinToken": "spirit_9", "players": ["percival", "LSA", "merlin", "LSA", "LSA", "minion of mordred/mordred", "minion of mordred/oberon", "LSA", "morgana"], "tokens": ["3", "4", "8", "92", "19", "1", "58", "52", "44", "84", "61", "35", "42", "43", "86", "41", "91", "75", "90", "70", "53", "88", "82", "23", "68", "76", "66", "14", "31", "33", "95", "55", "77", "81", "38", "99", "24", "0", "57", "9", "46", "5", "2", "12", "37", "79", "20", "22", "36", "80", "10", "29", "40", "17", "48", "18", "60", "32", "27", "28", "83", "7", "78", "30", "15", "6", "13", "49", "73", "63", "74", "16", "67", "59", "11", "65", "85", "47", "45", "96", "56", "94", "89", "39", "69", "64", "50", "97", "98", "21", "51", "71", "72", "34", "93", "26", "87", "62", "54", "25"], "numPlayers": 9}, {"joinToken": "spirit_10", "players": ["morgana", "LSA", "LSA", "LSA", "percival", "minion of mordred/oberon", "LSA", "merlin", "minion of mordred/mordred", "minion of mordred"], "tokens": ["15", "5", "89", "2", "41", "63", "55", "81", "3", "6", "56", "37", "94", "31", "38", "16", "60", "25", "30", "52", "32", "0", "71", "34", "98", "80", "76", "65", "49", "28", "83", "35", "87", "13", "69", "18", "21", "20", "86", "58", "85", "84", "73", "7", "66", "75", "36", "74", "96", "47", "97", "33", "78", "48", "42", "8", "62", "27", "70", "44", "46", "4", "57", "77", "99", "14", "88", "72", "95", "17", "9", "93", "92", "79", "50", "54", "40", "64", "45", "82", "39", "91", "59", "43", "61", "51", "53", "23", "26", "12", "10", "19", "22", "1", "24", "29", "90", "67", "11", "68"], "numPlayers": 10}, {"joinToken": "jetblue_5", "players": ["percival", "LSA", "minion of mordred/oberon", "morgana", "merlin"], "tokens": ["26", "45", "95", "38", "48", "97", "59", "73", "44", "50", "22", "8", "78", "70", "12", "13", "83", "77", "34", "7", "79", "35", "15", "81", "31", "67", "69", "19", "82", "98", "30", "24", "14", "86", "64", "88", "1", "42", "4", "75", "0", "9", "61", "96", "5", "58", "74", "3", "62", "6", "51", "41", "40", "68", "28", "60", "71", "11", "23", "99", "36", "93", "55", "20", "57", "21", "52", "85", "25", "46", "90", "39", "94", "76", "43", "92", "32", "2", "18", "27", "47", "16", "49", "56", "10", "89", "66", "33", "54", "72", "87", "84", "65", "37", "29", "63", "53", "80", "17", "91"], "numPlayers": 5}, {"joinToken": "jetblue_6", "players": ["minion of mordred/oberon", "percival", "merlin", "morgana", "LSA", "LSA"], "tokens": ["28", "94", "77", "45", "78", "4", "41", "67", "17", "79", "95", "31", "83", "25", "85", "40", "42", "72", "18", "96", "75", "71", "51", "55", "62", "37", "26", "1", "89", "11", "23", "39", "81", "27", "88", "53", "20", "19", "86", "14", "47", "29", "48", "87", "99", "63", "7", "3", "91", "15", "74", "13", "38", "68", "60", "16", "92", "82", "12", "54", "73", "84", "0", "76", "69", "24", "21", "50", "97", "8", "61", "65", "66", "98", "57", "46", "80", "93", "36", "59", "49", "35", "34", "90", "70", "9", "56", "32", "33", "44", "30", "22", "64", "2", "43", "6", "5", "52", "58", "10"], "numPlayers": 6}, {"joinToken": "jetblue_7", "players": ["LSA", "merlin", "minion of mordred/oberon", "minion of mordred/mordred", "LSA", "morgana", "percival"], "tokens": ["12", "53", "7", "98", "71", "3", "34", "0", "77", "80", "26", "88", "73", "85", "39", "36", "1", "16", "25", "32", "43", "62", "65", "48", "30", "55", "38", "70", "56", "59", "64", "78", "72", "44", "86", "68", "89", "57", "14", "87", "27", "47", "19", "49", "75", "28", "4", "37", "20", "6", "84", "76", "93", "13", "17", "18", "79", "50", "95", "91", "24", "10", "92", "83", "74", "35", "45", "22", "15", "41", "90", "81", "99", "29", "96", "23", "11", "82", "60", "52", "97", "40", "67", "63", "51", "66", "94", "31", "46", "33", "54", "2", "69", "8", "61", "9", "58", "5", "21", "42"], "numPlayers": 7}, {"joinToken": "jetblue_8", "players": ["minion of mordred/mordred", "merlin", "percival", "LSA", "LSA", "LSA", "minion of mordred/oberon", "morgana"], "tokens": ["86", "21", "24", "20", "28", "73", "2", "63", "54", "36", "12", "1", "98", "87", "72", "0", "96", "30", "84", "7", "52", "62", "17", "55", "26", "33", "51", "68", "90", "5", "67", "8", "57", "9", "71", "11", "79", "92", "42", "75", "85", "97", "39", "37", "45", "94", "35", "65", "74", "49", "60", "56", "78", "59", "43", "31", "83", "58", "88", "77", "32", "16", "14", "81", "61", "91", "44", "34", "48", "6", "4", "46", "38", "64", "25", "47", "69", "53", "80", "99", "89", "3", "13", "66", "10", "23", "76", "15", "70", "93", "82", "18", "22", "95", "27", "40", "29", "19", "41", "50"], "numPlayers": 8}, {"joinToken": "jetblue_9", "players": ["minion of mordred/mordred", "percival", "merlin", "morgana", "minion of mordred/oberon", "LSA", "LSA", "LSA", "LSA"], "tokens": ["86", "35", "83", "72", "17", "73", "2", "3", "71", "26", "13", "57", "40", "96", "43", "9", "66", "1", "19", "94", "34", "28", "63", "46", "77", "51", "88", "42", "81", "27", "85", "61", "91", "78", "87", "39", "58", "59", "14", "82", "69", "44", "67", "47", "32", "49", "41", "80", "95", "5", "21", "7", "30", "60", "70", "75", "74", "24", "29", "92", "84", "22", "33", "25", "15", "6", "62", "10", "52", "31", "37", "76", "90", "98", "97", "18", "56", "45", "68", "89", "4", "79", "38", "50", "53", "54", "48", "12", "55", "0", "93", "99", "64", "11", "8", "36", "20", "23", "65", "16"], "numPlayers": 9}, {"joinToken": "jetblue_10", "players": ["minion of mordred/oberon", "LSA", "LSA", "percival", "minion of mordred", "merlin", "morgana", "LSA", "LSA", "minion of mordred/mordred"], "tokens": ["37", "23", "82", "36", "74", "20", "46", "45", "9", "22", "62", "87", "17", "49", "11", "81", "1", "32", "26", "76", "90", "86", "15", "63", "56", "91", "66", "99", "67", "88", "39", "95", "0", "93", "44", "96", "28", "50", "77", "79", "34", "78", "58", "52", "19", "75", "16", "2", "3", "70", "29", "69", "43", "40", "41", "92", "31", "6", "27", "72", "42", "80", "98", "21", "97", "4", "61", "83", "10", "51", "53", "25", "38", "54", "18", "64", "55", "57", "73", "12", "59", "84", "68", "85", "35", "65", "48", "71", "60", "8", "94", "24", "7", "47", "13", "14", "5", "33", "30", "89"], "numPlayers": 10}]