[{"joinToken": "canada", "players": ["minion of mordred/oberon", "merlin", "LSA", "percival", "minion of mordred", "morgana", "LSA"], "tokens": ["36", "51", "26", "59", "0", "47", "24", "27", "50", "10", "37", "65", "64", "12", "20", "21", "45", "40", "14", "68", "69", "54", "57", "67", "7", "66", "8", "11", "2", "39", "55", "33", "49", "19", "35", "31", "53", "1", "30", "32", "18", "9", "44", "3", "16", "38", "17", "5", "61", "25", "29", "15", "23", "34", "48", "43", "22", "62", "63", "41", "58", "6", "56", "60", "28", "42", "13", "46", "4", "52"]}, {"joinToken": "delta", "players": ["minion of mordred/oberon", "morgana", "minion of mordred", "merlin", "LSA", "percival", "LSA"], "tokens": ["50", "19", "47", "5", "18", "21", "67", "43", "52", "8", "65", "1", "32", "23", "38", "64", "22", "46", "0", "61", "11", "59", "6", "42", "30", "39", "24", "16", "31", "66", "44", "34", "29", "17", "33", "56", "69", "36", "27", "54", "9", "7", "25", "10", "35", "4", "60", "13", "41", "28", "37", "57", "48", "2", "12", "15", "3", "45", "14", "62", "26", "63", "58", "51", "49", "55", "53", "68", "40", "20"]}, {"joinToken": "united", "players": ["morgana", "minion of mordred", "percival", "minion of mordred/oberon", "merlin", "LSA", "LSA"], "tokens": ["23", "20", "10", "16", "6", "42", "50", "40", "32", "66", "7", "62", "36", "69", "29", "12", "52", "15", "22", "25", "59", "18", "2", "4", "56", "37", "43", "67", "24", "21", "63", "65", "19", "28", "44", "8", "49", "39", "27", "9", "51", "68", "34", "13", "30", "33", "38", "48", "61", "0", "3", "17", "45", "11", "57", "55", "35", "1", "41", "46", "47", "14", "5", "64", "26", "54", "53", "60", "58", "31"]}, {"joinToken": "frontier", "players": ["percival", "LSA", "morgana", "minion of mordred/oberon", "minion of mordred", "LSA", "merlin"], "tokens": ["36", "68", "18", "3", "12", "45", "32", "46", "11", "59", "61", "35", "50", "1", "26", "41", "56", "5", "9", "8", "37", "31", "29", "7", "69", "43", "53", "19", "58", "27", "49", "34", "14", "10", "51", "17", "62", "15", "54", "25", "47", "24", "6", "65", "20", "39", "0", "44", "33", "13", "30", "4", "22", "38", "42", "2", "21", "67", "66", "57", "63", "48", "23", "60", "64", "16", "28", "55", "52", "40"]}, {"joinToken": "sw", "players": ["LSA", "merlin", "minion of mordred/oberon", "percival", "LSA", "morgana", "minion of mordred"], "tokens": ["46", "61", "16", "4", "2", "17", "21", "30", "20", "31", "55", "39", "43", "15", "54", "56", "57", "28", "3", "19", "52", "58", "35", "45", "14", "32", "48", "51", "33", "40", "26", "6", "69", "47", "42", "29", "23", "9", "27", "50", "11", "22", "67", "38", "8", "68", "65", "34", "60", "1", "66", "62", "44", "36", "37", "25", "59", "24", "18", "5", "41", "64", "63", "10", "53", "13", "12", "7", "0", "49"]}, {"joinToken": "alaska", "players": ["LSA", "minion of mordred", "minion of mordred/oberon", "percival", "merlin", "LSA", "morgana"], "tokens": ["15", "11", "61", "18", "33", "9", "54", "30", "6", "62", "41", "40", "24", "27", "64", "37", "25", "13", "53", "17", "57", "23", "22", "2", "47", "34", "68", "52", "38", "7", "29", "44", "67", "28", "49", "8", "0", "45", "5", "3", "43", "56", "63", "39", "32", "14", "46", "50", "16", "59", "58", "55", "31", "60", "65", "10", "19", "21", "66", "1", "20", "12", "69", "36", "42", "48", "35", "4", "51", "26"]}, {"joinToken": "american", "players": ["LSA", "LSA", "merlin", "minion of mordred", "percival", "minion of mordred/oberon", "morgana"], "tokens": ["45", "12", "17", "37", "9", "26", "15", "51", "68", "39", "20", "19", "57", "10", "58", "4", "42", "0", "64", "60", "7", "53", "55", "18", "28", "27", "36", "44", "65", "23", "41", "62", "63", "43", "32", "54", "21", "50", "47", "59", "33", "14", "69", "49", "52", "67", "35", "1", "40", "31", "8", "61", "34", "24", "25", "22", "16", "66", "30", "5", "48", "2", "6", "11", "29", "56", "13", "38", "3", "46"]}, {"joinToken": "spirit", "players": ["LSA", "morgana", "merlin", "minion of mordred/oberon", "LSA", "percival", "minion of mordred"], "tokens": ["60", "25", "19", "14", "41", "40", "20", "24", "35", "15", "51", "52", "42", "54", "6", "49", "32", "5", "18", "0", "23", "37", "34", "61", "8", "30", "38", "45", "43", "56", "7", "65", "21", "1", "62", "13", "17", "2", "27", "66", "4", "9", "10", "64", "31", "44", "39", "11", "47", "50", "48", "46", "69", "36", "67", "16", "3", "68", "57", "33", "63", "12", "58", "28", "29", "53", "55", "59", "22", "26"]}, {"joinToken": "jetblue", "players": ["minion of mordred/oberon", "morgana", "LSA", "minion of mordred", "merlin", "percival", "LSA"], "tokens": ["11", "31", "5", "24", "7", "65", "26", "19", "63", "10", "2", "41", "51", "48", "54", "27", "45", "40", "69", "37", "12", "20", "61", "46", "47", "57", "15", "59", "30", "32", "56", "67", "13", "52", "44", "60", "36", "34", "4", "58", "50", "28", "29", "43", "22", "33", "23", "55", "14", "21", "9", "16", "39", "53", "38", "6", "49", "25", "35", "42", "0", "18", "17", "64", "1", "62", "66", "8", "68", "3"]}]